<c:FragmentDefinition xmlns="sap.m" xmlns:c="sap.ui.core" xmlns:f="sap.ui.layout.form" xmlns:a="http://schemas.sap.com/sapui5/extension/sap.ui.core.CustomData/1"><Dialog draggable="true" titleAlignment="Center" resizable="true" afterClose="dialogAfterclose" title="{i18n>0242}" busyIndicatorDelay="0"><content><VBox class="sapUiSmallMargin"><f:Form editable="true"><f:layout><f:ResponsiveGridLayout labelSpanXL="3" labelSpanL="3" labelSpanM="3" labelSpanS="12" adjustLabelSpan="false" emptySpanXL="4" emptySpanL="4" emptySpanM="4" emptySpanS="0" columnsXL="1" columnsL="1" columnsM="1" singleContainerFullSize="false"/></f:layout><f:formContainers><f:FormContainer><f:formElements><f:FormElement label="{i18n>0240}"><f:fields><Input a:button="purchaseordertype" editable="{Settings>/IsCreateDocumentType}" name="BSART" required="true" showValueHelp="true" value="{Settings>/createdocumenttype/BSART}" valueHelpRequest=".searchHelp.onValueHelpRequest" valueHelpOnly="true"/></f:fields></f:FormElement><f:FormElement label="{i18n>0241}"><f:fields><Input a:button="plant" editable="{Settings>/IsCreateDocumentType}" maxLength="4" name="werks" placeholder="{i18n>0241}" required="true" showValueHelp="true" value="{Settings>/createdocumenttype/WERKS_F}" valueHelpRequest=".searchHelp.onValueHelpRequest" valueHelpOnly="true"/></f:fields></f:FormElement><f:FormElement label="{i18n>0244}"><f:fields><Input a:button="plant" maxLength="4" name="werks" placeholder="{i18n>0244}" showValueHelp="true" value="{Settings>/createdocumenttype/WERKS_T}" valueHelpRequest=".searchHelp.onValueHelpRequest" valueHelpOnly="true"/></f:fields></f:FormElement></f:formElements></f:FormContainer></f:formContainers></f:Form></VBox></content><buttons width="auto" class="sapUiNoMarginBegin sapUiNoMarginEnd"><Button text="{= ${Settings>/IsCreateDocumentType} === true ? ${i18n>Commons.0031} : ${i18n>Commons.0017}}" press="onCreateDocumentTypePress" enabled="true" type="Emphasized"/><Button text="{i18n>Commons.0007}" type="Reject" press="handleCloseDocumentTypeDialog"/></buttons></Dialog></c:FragmentDefinition>